config.py
server.py
conf/__init__.py
conf/custom_models.json
mseep_zen_mcp_server-5.11.1.data/data/conf/custom_models.json
mseep_zen_mcp_server-5.11.1.dist-info/licenses/LICENSE
providers/__init__.py
providers/base.py
providers/custom.py
providers/dial.py
providers/gemini.py
providers/openai_compatible.py
providers/openai_provider.py
providers/openrouter.py
providers/openrouter_registry.py
providers/registry.py
providers/xai.py
systemprompts/__init__.py
systemprompts/analyze_prompt.py
systemprompts/chat_prompt.py
systemprompts/codereview_prompt.py
systemprompts/consensus_prompt.py
systemprompts/debug_prompt.py
systemprompts/docgen_prompt.py
systemprompts/planner_prompt.py
systemprompts/precommit_prompt.py
systemprompts/refactor_prompt.py
systemprompts/secaudit_prompt.py
systemprompts/testgen_prompt.py
systemprompts/thinkdeep_prompt.py
systemprompts/tracer_prompt.py
tools/__init__.py
tools/analyze.py
tools/challenge.py
tools/chat.py
tools/codereview.py
tools/consensus.py
tools/debug.py
tools/docgen.py
tools/listmodels.py
tools/models.py
tools/planner.py
tools/precommit.py
tools/refactor.py
tools/secaudit.py
tools/testgen.py
tools/thinkdeep.py
tools/tracer.py
tools/version.py
tools/shared/__init__.py
tools/shared/base_models.py
tools/shared/base_tool.py
tools/shared/schema_builders.py
tools/simple/__init__.py
tools/simple/base.py
tools/workflow/__init__.py
tools/workflow/base.py
tools/workflow/schema_builders.py
tools/workflow/workflow_mixin.py
utils/__init__.py
utils/client_info.py
utils/conversation_memory.py
utils/file_types.py
utils/file_utils.py
utils/model_context.py
utils/model_restrictions.py
utils/security_config.py
utils/storage_backend.py
utils/token_utils.py
mseep_zen_mcp_server-5.11.1.dist-info/METADATA
mseep_zen_mcp_server-5.11.1.dist-info/WHEEL
mseep_zen_mcp_server-5.11.1.dist-info/entry_points.txt
mseep_zen_mcp_server-5.11.1.dist-info/top_level.txt
mseep_zen_mcp_server-5.11.1.dist-info/RECORD
