Metadata-Version: 2.4
Name: mseep-zen-mcp-server
Version: 5.11.1
Summary: AI-powered MCP server with multiple model providers
Author-email: mseep <support@skydeck.ai>
Requires-Python: >=3.9
License-File: LICENSE
Requires-Dist: mcp>=1.0.0
Requires-Dist: google-genai>=1.19.0
Requires-Dist: openai>=1.55.2
Requires-Dist: pydantic>=2.0.0
Requires-Dist: python-dotenv>=1.0.0
Dynamic: license-file
